randomAccessReader/__init__.py
random_access_file_reader-0.3.0.dist-info/DESCRIPTION.rst
random_access_file_reader-0.3.0.dist-info/METADATA
random_access_file_reader-0.3.0.dist-info/RECORD
random_access_file_reader-0.3.0.dist-info/WHEEL
random_access_file_reader-0.3.0.dist-info/metadata.json
random_access_file_reader-0.3.0.dist-info/top_level.txt
