Metadata-Version: 2.0
Name: random-access-file-reader
Version: 0.3.0
Summary: A python random access file reader
Home-page: https://github.com/jegesh/python-random-access-file-reader
Author: Yaakov Gesher
Author-email: yaakov@gesher.net
License: Apache Software License
Platform: UNKNOWN
Classifier: Development Status :: 3 - Alpha
Classifier: Intended Audience :: Developers
Classifier: Topic :: Software Development :: Libraries
Classifier: License :: OSI Approved :: Apache Software License
Classifier: Programming Language :: Python :: 2.7
Classifier: Programming Language :: Python :: 3.5
